lib_idoc/__init__.py
lib_idoc/invoice.py
lib_idoc-0.1.6.dist-info/METADATA
lib_idoc-0.1.6.dist-info/WHEEL
lib_idoc-0.1.6.dist-info/RECORD
