Metadata-Version: 2.3
Name: lib-idoc
Version: 0.1.6
Summary: 
Author: Nathan Blum
Author-email: n.blum@student.tudelft.nl
Requires-Python: >=3.10
Classifier: Programming Language :: Python :: 3
Classifier: Programming Language :: Python :: 3.10
Classifier: Programming Language :: Python :: 3.11
Classifier: Programming Language :: Python :: 3.12
Classifier: Programming Language :: Python :: 3.13
Requires-Dist: lib-invoice (>=0.1.1,<0.2.0)
Requires-Dist: lib-utilys (>=0.1.3,<0.2.0)
